scripts/__init__.py
scripts/run_sally.py
selenium_yaml/__init__.py
selenium_yaml/driver_utils.py
selenium_yaml/exceptions.py
selenium_yaml/fields.py
selenium_yaml/parsers.py
selenium_yaml/validators.py
selenium_yaml/steps/__init__.py
selenium_yaml/steps/core_steps.py
selenium_yaml/steps/registered_steps.py
selenium_yaml/steps/resolvers.py
selenium_yaml-1.0.98.data/scripts/run_sally.py
selenium_yaml-1.0.98.dist-info/licenses/LICENSE
tests/__init__.py
tests/test_fields.py
tests/test_resolvers.py
tests/test_steps.py
tests/test_validators.py
selenium_yaml-1.0.98.dist-info/METADATA
selenium_yaml-1.0.98.dist-info/WHEEL
selenium_yaml-1.0.98.dist-info/top_level.txt
selenium_yaml-1.0.98.dist-info/RECORD
